<?xml version = '1.0' encoding = 'UTF-8'?>
<Relation class="oracle.dbtools.crest.model.design.logical.Relation" name="DOCTOR_to_APP_USER" directorySegmentName="seg_0" id="AE3D9B08-D8F6-83C5-BB7E-975C4782AAC3">
<createdBy>poojadoddannavar</createdBy>
<createdTime>2026-03-19 01:29:35 UTC</createdTime>
<ownerDesignName>HospitalMngmntSystem</ownerDesignName>
<engineerTo>
<item key="08A367C7-F2E9-8C83-C067-6B258478ACE9" value="true"/>
</engineerTo>
<sourcePk>52CEDFE3-AB5B-A6B1-AA18-6F59C2BDCB43</sourcePk>
<identifying>false</identifying>
<optionalSource>true</optionalSource>
<optionalTarget>true</optionalTarget>
<sourceCardinality>1</sourceCardinality>
<sourceEntity>6781AE8D-9EBC-4C13-90E5-B72CAED96117</sourceEntity>
<targetCardinalityString>*</targetCardinalityString>
<targetEntity>114F1437-93B6-ACA9-0CB2-591644A3637E</targetEntity>
<transferable>true</transferable>
<deleteRule>NO ACTION</deleteRule>
</Relation>
